images/ptov-pic1.png
images/ptov-pic2.png
images/ptov-pic3.png
netbox_ptov/__init__.py
netbox_ptov/_version.py
netbox_ptov/filtersets.py
netbox_ptov/forms.py
netbox_ptov/models.py
netbox_ptov/navigation.py
netbox_ptov/tables.py
netbox_ptov/urls.py
netbox_ptov/views.py
netbox_ptov/api/__init__.py
netbox_ptov/api/serializers.py
netbox_ptov/api/urls.py
netbox_ptov/api/views.py
netbox_ptov/migrations/0001_initial.py
netbox_ptov/migrations/__init__.py
netbox_ptov/templates/golab.html
netbox_ptov/templates/vlab_result.html
netbox_ptov/templates/netbox_ptov/gns3srv.html
netbox_ptov/templates/netbox_ptov/ptovjob.html
netbox_ptov/templates/netbox_ptov/switchtojob.html
netbox_ptov/tests/test_forms.py
netbox_ptov-0.2.0.5.dist-info/LICENSE
netbox_ptov-0.2.0.5.dist-info/METADATA
netbox_ptov-0.2.0.5.dist-info/WHEEL
netbox_ptov-0.2.0.5.dist-info/top_level.txt
netbox_ptov-0.2.0.5.dist-info/RECORD
