Metadata-Version: 2.2
Name: netbox_ptov
Version: 0.2.0.5
Summary: NetBox plugin for ptov.  Uses ptovnetlab project.
Author-email: Mencken Davidson <mencken@gmail.com>
Maintainer-email: Mencken Davidson <mencken@gmail.com>
License: 
Project-URL: Documentation, https://github.com/menckend/netbox_ptov/blob/main/README.md
Project-URL: Source, https://github.com/menckend/netbox_ptov
Project-URL: Tracker, https://github.com/menckend/netbox_ptov/issues
Keywords: netbox,plugin,arista,eapi,eos,gns3,lab,virtual,ceos
Classifier: Development Status :: 3 - Alpha
Classifier: Intended Audience :: Developers
Classifier: Natural Language :: English
Classifier: Programming Language :: Python :: 3 :: Only
Classifier: Programming Language :: Python :: 3.10
Classifier: Programming Language :: Python :: 3.11
Classifier: Programming Language :: Python :: 3.12
Requires-Python: >=3.12
License-File: LICENSE
Requires-Dist: ptovnetlab
Requires-Dist: build
Provides-Extra: test
Requires-Dist: black==24.3.0; extra == "test"
Requires-Dist: check-manifest==0.49; extra == "test"
Requires-Dist: flake8; extra == "test"
Requires-Dist: flake8-pyproject; extra == "test"
Requires-Dist: pre-commit==3.7.0; extra == "test"
Requires-Dist: pytest==8.1.1; extra == "test"
